MANIFEST.in
README.md
setup.cfg
setup.py
context_providers/__init__.py
context_providers/hh_provider.py
opensource_watchman/__init__.py
opensource_watchman/common_types.py
opensource_watchman/config.py
opensource_watchman/output_processors.py
opensource_watchman/prerequisites.py
opensource_watchman/run.py
opensource_watchman.egg-info/PKG-INFO
opensource_watchman.egg-info/SOURCES.txt
opensource_watchman.egg-info/dependency_links.txt
opensource_watchman.egg-info/entry_points.txt
opensource_watchman.egg-info/not-zip-safe
opensource_watchman.egg-info/requires.txt
opensource_watchman.egg-info/top_level.txt
opensource_watchman/api/__init__.py
opensource_watchman/api/codeclimate_api.py
opensource_watchman/api/github.py
opensource_watchman/api/pypistats.py
opensource_watchman/api/travis.py
opensource_watchman/pipelines/__init__.py
opensource_watchman/pipelines/extended_repo_info.py
opensource_watchman/pipelines/github.py
opensource_watchman/pipelines/master.py
opensource_watchman/pipelines/travis.py
opensource_watchman/templates/report_template.html
opensource_watchman/utils/__init__.py
opensource_watchman/utils/images.py
opensource_watchman/utils/logs_analiser.py