Metadata-Version: 2.1
Name: opensource-watchman
Version: 0.0.1
Summary: Opensource repos validator.
Home-page: https://github.com/Melevir/opensource_watchman
Author: Ilya Lebedev
Author-email: melevir@gmail.com
License: MIT
Keywords: plugins
Platform: UNKNOWN
Classifier: Environment :: Console
Classifier: Operating System :: OS Independent
Classifier: Topic :: Software Development :: Libraries :: Python Modules
Classifier: Topic :: Software Development :: Quality Assurance
Classifier: Programming Language :: Python
Classifier: Programming Language :: Python :: 3.7
Classifier: Programming Language :: Python :: 3.8
